FitTransit/Transit_class.py
FitTransit/__init__.py
FitTransit/ga.py
FitTransit/info_ga.py
FitTransit/info_mc.py
FitTransit-0.1.2.dist-info/METADATA
FitTransit-0.1.2.dist-info/WHEEL
FitTransit-0.1.2.dist-info/top_level.txt
FitTransit-0.1.2.dist-info/RECORD
