Metadata-Version: 2.1
Name: FitTransit
Version: 0.1.2
Summary: Fitting transits of exoplanets
Home-page: https://github.com/pavolgaj/FitTransit
Author: Pavol Gajdos
Classifier: Development Status :: 3 - Alpha
Classifier: Programming Language :: Python :: 3
Classifier: Topic :: Scientific/Engineering :: Astronomy
Requires-Dist: numpy >=1.10.2
Requires-Dist: matplotlib >=1.5.0
Requires-Dist: scipy >=1.5.0
Requires-Dist: batman-package >=2.4.0
Provides-Extra: mcmc
Requires-Dist: emcee >=3.0.0 ; extra == 'mcmc'
Requires-Dist: corner ; extra == 'mcmc'
Requires-Dist: tqdm ; extra == 'mcmc'
